{
  "metadata": {
    "source": "../pages/Daniel-Z.htm",
    "title": "Daniel Zantedeschi | USF Muma College of Business",
    "keywords": "",
    "description": "",
    "extractor_used": "main_content_well"
  },
  "chunks": [
    {
      "content": "Assistant Professordanielz@usf.eduRoom: CIS 1040Phone: (813) 974-5524Vita Daniel Zantedeschi is an assistant professor in the School of Information Systems\n               and Management, joining the full-time faculty in August, 2019. He comes from the Fisher\n               College of Business at The Ohio State University, where he was an assistant professor\n               in marketing and logistics. Prior to that, he was an assistant professor in the Muma\n               College of Business where he was affiliated with the Center for Analytics and Creativity\n               and the Interdisciplinary Consortium for Data Sciences. His research interests include digital multi-channel Attributi9on, Advertising, Pricing\n               and promotions management and various topics in statistical methodology, data science\n               and computer skills. Zantedeschi earned a PhD in information risk and Operations management and a masters’",
      "metadata": {
        "source": "../pages/Daniel-Z.htm",
        "title": "Daniel Zantedeschi | USF Muma College of Business",
        "keywords": "",
        "description": "",
        "extractor_used": "main_content_well"
      }
    },
    {
      "content": "and computer skills. Zantedeschi earned a PhD in information risk and Operations management and a masters’\n               degree in economics from the University of Texas, Austin. He received a master’s degree\n               in statistics and stochastic modeling from the University of California, Santa Cruz",
      "metadata": {
        "source": "../pages/Daniel-Z.htm",
        "title": "Daniel Zantedeschi | USF Muma College of Business",
        "keywords": "",
        "description": "",
        "extractor_used": "main_content_well"
      }
    }
  ]
}